monsh.py
monsh-1.0.3.dist-info/METADATA
monsh-1.0.3.dist-info/WHEEL
monsh-1.0.3.dist-info/entry_points.txt
monsh-1.0.3.dist-info/top_level.txt
monsh-1.0.3.dist-info/RECORD
