Metadata-Version: 2.1
Name: monsh
Version: 1.0.3
Summary: This package contains the client side script for mon.sh which allows you to sync your command output to the cloud.
Home-page: https://www.mon.sh/
Author: Ameer Ayoub
Author-email: ameer.ayoub@gmail.com
Classifier: Development Status :: 4 - Beta
Classifier: Intended Audience :: Developers
Classifier: Intended Audience :: Information Technology
Classifier: License :: OSI Approved :: MIT License
Classifier: Natural Language :: English
Classifier: Topic :: System :: Monitoring
Classifier: Topic :: System :: Logging
Classifier: Topic :: System :: Shells
Classifier: Topic :: System :: System Shells
Classifier: Topic :: Terminals
Classifier: Topic :: Utilities
Requires-Dist: requests
